{
	"archive" : 
	{
		"lto" : true
	},
	"artifacts" : 
	[
		{
			"path" : "lib/libhibf.a"
		}
	],
	"backtrace" : 1,
	"backtraceGraph" : 
	{
		"commands" : 
		[
			"add_library",
			"target_compile_options",
			"target_link_libraries",
			"target_compile_definitions",
			"target_include_directories",
			"target_compile_features"
		],
		"files" : 
		[
			"build/_deps/hibf-src/src/CMakeLists.txt"
		],
		"nodes" : 
		[
			{
				"file" : 0
			},
			{
				"command" : 0,
				"file" : 0,
				"line" : 29,
				"parent" : 0
			},
			{
				"command" : 1,
				"file" : 0,
				"line" : 33,
				"parent" : 0
			},
			{
				"command" : 2,
				"file" : 0,
				"line" : 36,
				"parent" : 0
			},
			{
				"command" : 3,
				"file" : 0,
				"line" : 31,
				"parent" : 0
			},
			{
				"command" : 4,
				"file" : 0,
				"line" : 38,
				"parent" : 0
			},
			{
				"command" : 5,
				"file" : 0,
				"line" : 32,
				"parent" : 0
			}
		]
	},
	"compileGroups" : 
	[
		{
			"compileCommandFragments" : 
			[
				{
					"fragment" : "-g -std=c++23 -flto=auto -arch arm64 -isysroot /Library/Developer/CommandLineTools/SDKs/MacOSX14.sdk"
				},
				{
					"backtrace" : 2,
					"fragment" : "-Wno-psabi"
				},
				{
					"backtrace" : 2,
					"fragment" : "-march=native"
				},
				{
					"backtrace" : 3,
					"fragment" : "-fopenmp"
				}
			],
			"defines" : 
			[
				{
					"backtrace" : 4,
					"define" : "HIBF_UNINITIALISED_RESIZE"
				},
				{
					"backtrace" : 4,
					"define" : "SIMDE_ENABLE_OPENMP"
				}
			],
			"includes" : 
			[
				{
					"backtrace" : 5,
					"path" : "/Users/mostafaelkhatib/Desktop/swp-25-repo/swp25-tutorial/build/_deps/hibf-src/include"
				},
				{
					"backtrace" : 3,
					"isSystem" : true,
					"path" : "/Users/mostafaelkhatib/Desktop/swp-25-repo/swp25-tutorial/build/_deps/cereal-src/include"
				},
				{
					"backtrace" : 3,
					"isSystem" : true,
					"path" : "/Users/mostafaelkhatib/Desktop/swp-25-repo/swp25-tutorial/build/_deps/simde-src"
				}
			],
			"language" : "CXX",
			"languageStandard" : 
			{
				"backtraces" : 
				[
					6,
					3
				],
				"standard" : "23"
			},
			"sourceIndexes" : 
			[
				0,
				1,
				2,
				3,
				4,
				5,
				6,
				7,
				8,
				9,
				10,
				11,
				12,
				13,
				14,
				15,
				16,
				17,
				18
			]
		}
	],
	"id" : "hibf::@77fef9da0b28ed0d618f",
	"name" : "hibf",
	"nameOnDisk" : "libhibf.a",
	"paths" : 
	{
		"build" : "_deps/hibf-build/src",
		"source" : "build/_deps/hibf-src/src"
	},
	"sourceGroups" : 
	[
		{
			"name" : "Source Files",
			"sourceIndexes" : 
			[
				0,
				1,
				2,
				3,
				4,
				5,
				6,
				7,
				8,
				9,
				10,
				11,
				12,
				13,
				14,
				15,
				16,
				17,
				18
			]
		}
	],
	"sources" : 
	[
		{
			"backtrace" : 1,
			"compileGroupIndex" : 0,
			"path" : "build/_deps/hibf-src/src/hierarchical_interleaved_bloom_filter.cpp",
			"sourceGroupIndex" : 0
		},
		{
			"backtrace" : 1,
			"compileGroupIndex" : 0,
			"path" : "build/_deps/hibf-src/src/interleaved_bloom_filter.cpp",
			"sourceGroupIndex" : 0
		},
		{
			"backtrace" : 1,
			"compileGroupIndex" : 0,
			"path" : "build/_deps/hibf-src/src/config.cpp",
			"sourceGroupIndex" : 0
		},
		{
			"backtrace" : 1,
			"compileGroupIndex" : 0,
			"path" : "build/_deps/hibf-src/src/layout/simple_binning.cpp",
			"sourceGroupIndex" : 0
		},
		{
			"backtrace" : 1,
			"compileGroupIndex" : 0,
			"path" : "build/_deps/hibf-src/src/layout/layout.cpp",
			"sourceGroupIndex" : 0
		},
		{
			"backtrace" : 1,
			"compileGroupIndex" : 0,
			"path" : "build/_deps/hibf-src/src/layout/compute_fpr_correction.cpp",
			"sourceGroupIndex" : 0
		},
		{
			"backtrace" : 1,
			"compileGroupIndex" : 0,
			"path" : "build/_deps/hibf-src/src/layout/compute_layout.cpp",
			"sourceGroupIndex" : 0
		},
		{
			"backtrace" : 1,
			"compileGroupIndex" : 0,
			"path" : "build/_deps/hibf-src/src/layout/compute_relaxed_fpr_correction.cpp",
			"sourceGroupIndex" : 0
		},
		{
			"backtrace" : 1,
			"compileGroupIndex" : 0,
			"path" : "build/_deps/hibf-src/src/layout/data_store.cpp",
			"sourceGroupIndex" : 0
		},
		{
			"backtrace" : 1,
			"compileGroupIndex" : 0,
			"path" : "build/_deps/hibf-src/src/sketch/compute_sketches.cpp",
			"sourceGroupIndex" : 0
		},
		{
			"backtrace" : 1,
			"compileGroupIndex" : 0,
			"path" : "build/_deps/hibf-src/src/layout/graph.cpp",
			"sourceGroupIndex" : 0
		},
		{
			"backtrace" : 1,
			"compileGroupIndex" : 0,
			"path" : "build/_deps/hibf-src/src/layout/hierarchical_binning.cpp",
			"sourceGroupIndex" : 0
		},
		{
			"backtrace" : 1,
			"compileGroupIndex" : 0,
			"path" : "build/_deps/hibf-src/src/misc/print.cpp",
			"sourceGroupIndex" : 0
		},
		{
			"backtrace" : 1,
			"compileGroupIndex" : 0,
			"path" : "build/_deps/hibf-src/src/sketch/toolbox.cpp",
			"sourceGroupIndex" : 0
		},
		{
			"backtrace" : 1,
			"compileGroupIndex" : 0,
			"path" : "build/_deps/hibf-src/src/sketch/hyperloglog.cpp",
			"sourceGroupIndex" : 0
		},
		{
			"backtrace" : 1,
			"compileGroupIndex" : 0,
			"path" : "build/_deps/hibf-src/src/sketch/minhashes.cpp",
			"sourceGroupIndex" : 0
		},
		{
			"backtrace" : 1,
			"compileGroupIndex" : 0,
			"path" : "build/_deps/hibf-src/src/build/insert_into_ibf.cpp",
			"sourceGroupIndex" : 0
		},
		{
			"backtrace" : 1,
			"compileGroupIndex" : 0,
			"path" : "build/_deps/hibf-src/src/build/compute_kmers.cpp",
			"sourceGroupIndex" : 0
		},
		{
			"backtrace" : 1,
			"compileGroupIndex" : 0,
			"path" : "build/_deps/hibf-src/src/build/construct_ibf.cpp",
			"sourceGroupIndex" : 0
		}
	],
	"type" : "STATIC_LIBRARY"
}
